{
  "functions": [
    {
      "name": "user_passes_test",
      "params": [
        {
          "prefix": "",
          "name": "test_func",
          "annotation": null
        },
        {
          "prefix": "",
          "name": "login_url",
          "annotation": null
        },
        {
          "prefix": "",
          "name": "redirect_field_name",
          "annotation": null
        }
      ],
      "docstring": "\"\"\"\n    Decorator for views that checks that the user passes the given test,\n    redirecting to the log-in page if necessary. The test should be a callable\n    that takes the user object and returns True if the user passes.\n    \"\"\""
    },
    {
      "name": "login_required",
      "params": [
        {
          "prefix": "",
          "name": "function",
          "annotation": null
        },
        {
          "prefix": "",
          "name": "redirect_field_name",
          "annotation": null
        },
        {
          "prefix": "",
          "name": "login_url",
          "annotation": null
        }
      ],
      "docstring": "\"\"\"\n    Decorator for views that checks that the user is logged in, redirecting\n    to the log-in page if necessary.\n    \"\"\""
    },
    {
      "name": "permission_required",
      "params": [
        {
          "prefix": "",
          "name": "perm",
          "annotation": null
        },
        {
          "prefix": "",
          "name": "login_url",
          "annotation": null
        },
        {
          "prefix": "",
          "name": "raise_exception",
          "annotation": null
        }
      ],
      "docstring": "\"\"\"\n    Decorator for views that checks whether a user has a particular permission\n    enabled, redirecting to the log-in page if necessary.\n    If the raise_exception parameter is given the PermissionDenied exception\n    is raised.\n    \"\"\""
    }
  ],
  "classes": []
}